package com.badlogic.gdx.graphics;

final class m
{
  private static final byte[] eh = new byte[32000];
  private static final byte[] ei = new byte[32000];

  // ERROR //
  public static i b(com.badlogic.gdx.b.a parama)
  {
    // Byte code:
    //   0: new 19	java/io/DataInputStream
    //   3: dup
    //   4: new 21	java/util/zip/InflaterInputStream
    //   7: dup
    //   8: new 23	java/io/BufferedInputStream
    //   11: dup
    //   12: aload_0
    //   13: invokevirtual 29	com/badlogic/gdx/b/a:u	()Ljava/io/InputStream;
    //   16: invokespecial 33	java/io/BufferedInputStream:<init>	(Ljava/io/InputStream;)V
    //   19: invokespecial 34	java/util/zip/InflaterInputStream:<init>	(Ljava/io/InputStream;)V
    //   22: invokespecial 35	java/io/DataInputStream:<init>	(Ljava/io/InputStream;)V
    //   25: astore_1
    //   26: new 37	com/badlogic/gdx/graphics/i
    //   29: dup
    //   30: aload_1
    //   31: invokevirtual 41	java/io/DataInputStream:readInt	()I
    //   34: aload_1
    //   35: invokevirtual 41	java/io/DataInputStream:readInt	()I
    //   38: aload_1
    //   39: invokevirtual 41	java/io/DataInputStream:readInt	()I
    //   42: invokestatic 47	com/badlogic/gdx/graphics/k:f	(I)Lcom/badlogic/gdx/graphics/k;
    //   45: invokespecial 50	com/badlogic/gdx/graphics/i:<init>	(IILcom/badlogic/gdx/graphics/k;)V
    //   48: astore_2
    //   49: aload_2
    //   50: invokevirtual 54	com/badlogic/gdx/graphics/i:Y	()Ljava/nio/ByteBuffer;
    //   53: astore 6
    //   55: aload 6
    //   57: iconst_0
    //   58: invokevirtual 60	java/nio/ByteBuffer:position	(I)Ljava/nio/Buffer;
    //   61: pop
    //   62: aload 6
    //   64: aload 6
    //   66: invokevirtual 63	java/nio/ByteBuffer:capacity	()I
    //   69: invokevirtual 66	java/nio/ByteBuffer:limit	(I)Ljava/nio/Buffer;
    //   72: pop
    //   73: getstatic 13	com/badlogic/gdx/graphics/m:ei	[B
    //   76: astore 9
    //   78: aload 9
    //   80: monitorenter
    //   81: aload_1
    //   82: getstatic 13	com/badlogic/gdx/graphics/m:ei	[B
    //   85: invokevirtual 70	java/io/DataInputStream:read	([B)I
    //   88: istore 11
    //   90: iload 11
    //   92: ifle +70 -> 162
    //   95: aload 6
    //   97: getstatic 13	com/badlogic/gdx/graphics/m:ei	[B
    //   100: iconst_0
    //   101: iload 11
    //   103: invokevirtual 74	java/nio/ByteBuffer:put	([BII)Ljava/nio/ByteBuffer;
    //   106: pop
    //   107: goto -26 -> 81
    //   110: astore 10
    //   112: aload 9
    //   114: monitorexit
    //   115: aload 10
    //   117: athrow
    //   118: astore 5
    //   120: new 76	com/badlogic/gdx/utils/f
    //   123: dup
    //   124: new 78	java/lang/StringBuilder
    //   127: dup
    //   128: ldc 80
    //   130: invokespecial 83	java/lang/StringBuilder:<init>	(Ljava/lang/String;)V
    //   133: aload_0
    //   134: invokevirtual 87	java/lang/StringBuilder:append	(Ljava/lang/Object;)Ljava/lang/StringBuilder;
    //   137: ldc 89
    //   139: invokevirtual 92	java/lang/StringBuilder:append	(Ljava/lang/String;)Ljava/lang/StringBuilder;
    //   142: invokevirtual 96	java/lang/StringBuilder:toString	()Ljava/lang/String;
    //   145: aload 5
    //   147: invokespecial 99	com/badlogic/gdx/utils/f:<init>	(Ljava/lang/String;Ljava/lang/Throwable;)V
    //   150: athrow
    //   151: astore_3
    //   152: aload_1
    //   153: ifnull +7 -> 160
    //   156: aload_1
    //   157: invokevirtual 102	java/io/DataInputStream:close	()V
    //   160: aload_3
    //   161: athrow
    //   162: aload 9
    //   164: monitorexit
    //   165: aload 6
    //   167: iconst_0
    //   168: invokevirtual 60	java/nio/ByteBuffer:position	(I)Ljava/nio/Buffer;
    //   171: pop
    //   172: aload 6
    //   174: aload 6
    //   176: invokevirtual 63	java/nio/ByteBuffer:capacity	()I
    //   179: invokevirtual 66	java/nio/ByteBuffer:limit	(I)Ljava/nio/Buffer;
    //   182: pop
    //   183: aload_1
    //   184: invokevirtual 102	java/io/DataInputStream:close	()V
    //   187: aload_2
    //   188: areturn
    //   189: astore 15
    //   191: aload_2
    //   192: areturn
    //   193: astore 4
    //   195: goto -35 -> 160
    //   198: astore_3
    //   199: aconst_null
    //   200: astore_1
    //   201: goto -49 -> 152
    //   204: astore 5
    //   206: aconst_null
    //   207: astore_1
    //   208: goto -88 -> 120
    //
    // Exception table:
    //   from	to	target	type
    //   81	90	110	finally
    //   95	107	110	finally
    //   162	165	110	finally
    //   26	81	118	java/lang/Exception
    //   112	118	118	java/lang/Exception
    //   165	183	118	java/lang/Exception
    //   26	81	151	finally
    //   112	118	151	finally
    //   120	151	151	finally
    //   165	183	151	finally
    //   183	187	189	java/lang/Exception
    //   156	160	193	java/lang/Exception
    //   0	26	198	finally
    //   0	26	204	java/lang/Exception
  }
}

/* Location:           /home/danghvu/0day/WeChat/WeChat_4.5_dex2jar.jar
 * Qualified Name:     com.badlogic.gdx.graphics.m
 * JD-Core Version:    0.6.2
 */