package unk.com.tencent.mm.ad.a;

final class w
  implements Runnable
{
  w(v paramv)
  {
  }

  // ERROR //
  public final void run()
  {
    // Byte code:
    //   0: aload_0
    //   1: getfield 12	com/tencent/mm/ad/a/w:afx	Lcom/tencent/mm/ad/a/v;
    //   4: invokestatic 30	com/tencent/mm/ad/a/v:c	(Lcom/tencent/mm/ad/a/v;)Ljava/net/Socket;
    //   7: aload_0
    //   8: getfield 12	com/tencent/mm/ad/a/w:afx	Lcom/tencent/mm/ad/a/v;
    //   11: invokestatic 34	com/tencent/mm/ad/a/v:a	(Lcom/tencent/mm/ad/a/v;)Ljava/net/SocketAddress;
    //   14: aload_0
    //   15: getfield 12	com/tencent/mm/ad/a/w:afx	Lcom/tencent/mm/ad/a/v;
    //   18: invokestatic 38	com/tencent/mm/ad/a/v:b	(Lcom/tencent/mm/ad/a/v;)I
    //   21: invokevirtual 44	java/net/Socket:connect	(Ljava/net/SocketAddress;I)V
    //   24: aload_0
    //   25: getfield 12	com/tencent/mm/ad/a/w:afx	Lcom/tencent/mm/ad/a/v;
    //   28: invokestatic 48	com/tencent/mm/ad/a/v:d	(Lcom/tencent/mm/ad/a/v;)Ljava/lang/Object;
    //   31: astore_3
    //   32: aload_3
    //   33: monitorenter
    //   34: aload_0
    //   35: getfield 12	com/tencent/mm/ad/a/w:afx	Lcom/tencent/mm/ad/a/v;
    //   38: invokestatic 30	com/tencent/mm/ad/a/v:c	(Lcom/tencent/mm/ad/a/v;)Ljava/net/Socket;
    //   41: invokevirtual 52	java/net/Socket:isConnected	()Z
    //   44: ifeq +12 -> 56
    //   47: aload_0
    //   48: getfield 12	com/tencent/mm/ad/a/w:afx	Lcom/tencent/mm/ad/a/v;
    //   51: iconst_0
    //   52: invokestatic 55	com/tencent/mm/ad/a/v:a	(Lcom/tencent/mm/ad/a/v;I)I
    //   55: pop
    //   56: aload_0
    //   57: getfield 12	com/tencent/mm/ad/a/w:afx	Lcom/tencent/mm/ad/a/v;
    //   60: invokestatic 59	com/tencent/mm/ad/a/v:e	(Lcom/tencent/mm/ad/a/v;)Z
    //   63: ifne +17 -> 80
    //   66: aload_0
    //   67: getfield 12	com/tencent/mm/ad/a/w:afx	Lcom/tencent/mm/ad/a/v;
    //   70: invokestatic 62	com/tencent/mm/ad/a/v:f	(Lcom/tencent/mm/ad/a/v;)I
    //   73: istore 6
    //   75: iload 6
    //   77: ifeq +13 -> 90
    //   80: aload_0
    //   81: getfield 12	com/tencent/mm/ad/a/w:afx	Lcom/tencent/mm/ad/a/v;
    //   84: invokestatic 30	com/tencent/mm/ad/a/v:c	(Lcom/tencent/mm/ad/a/v;)Ljava/net/Socket;
    //   87: invokevirtual 65	java/net/Socket:close	()V
    //   90: aload_0
    //   91: getfield 12	com/tencent/mm/ad/a/w:afx	Lcom/tencent/mm/ad/a/v;
    //   94: invokestatic 48	com/tencent/mm/ad/a/v:d	(Lcom/tencent/mm/ad/a/v;)Ljava/lang/Object;
    //   97: invokevirtual 68	java/lang/Object:notify	()V
    //   100: aload_3
    //   101: monitorexit
    //   102: return
    //   103: astore 10
    //   105: aload_0
    //   106: getfield 12	com/tencent/mm/ad/a/w:afx	Lcom/tencent/mm/ad/a/v;
    //   109: iconst_1
    //   110: invokestatic 55	com/tencent/mm/ad/a/v:a	(Lcom/tencent/mm/ad/a/v;I)I
    //   113: pop
    //   114: goto -90 -> 24
    //   117: astore 8
    //   119: aload_0
    //   120: getfield 12	com/tencent/mm/ad/a/w:afx	Lcom/tencent/mm/ad/a/v;
    //   123: iconst_3
    //   124: invokestatic 55	com/tencent/mm/ad/a/v:a	(Lcom/tencent/mm/ad/a/v;I)I
    //   127: pop
    //   128: goto -104 -> 24
    //   131: astore_1
    //   132: aload_0
    //   133: getfield 12	com/tencent/mm/ad/a/w:afx	Lcom/tencent/mm/ad/a/v;
    //   136: iconst_2
    //   137: invokestatic 55	com/tencent/mm/ad/a/v:a	(Lcom/tencent/mm/ad/a/v;I)I
    //   140: pop
    //   141: goto -117 -> 24
    //   144: astore 4
    //   146: aload_3
    //   147: monitorexit
    //   148: aload 4
    //   150: athrow
    //   151: astore 5
    //   153: goto -63 -> 90
    //
    // Exception table:
    //   from	to	target	type
    //   0	24	103	java/net/ConnectException
    //   0	24	117	java/net/SocketException
    //   0	24	131	java/io/IOException
    //   34	56	144	finally
    //   56	75	144	finally
    //   80	90	144	finally
    //   90	102	144	finally
    //   80	90	151	java/lang/Exception
  }
}

/* Location:           /home/danghvu/0day/WeChat/WeChat_4.5_dex2jar.jar
 * Qualified Name:     com.tencent.mm.ad.a.w
 * JD-Core Version:    0.6.2
 */